sunset_mcp_calculator/__init__.py
sunset_mcp_calculator/__main__.py
sunset_mcp_calculator/server.py
sunset_mcp_calculator-0.1.7.dist-info/METADATA
sunset_mcp_calculator-0.1.7.dist-info/WHEEL
sunset_mcp_calculator-0.1.7.dist-info/entry_points.txt
sunset_mcp_calculator-0.1.7.dist-info/RECORD
