Metadata-Version: 2.4
Name: sunset_mcp_calculator
Version: 0.1.7
Summary: a mcp calculator
Requires-Python: >=3.12
Requires-Dist: build>=1.2.2.post1
Requires-Dist: mcp[cli]>=1.9.2
Requires-Dist: twine>=6.1.0
